drf_spreadsheets/__init__.py
drf_spreadsheets/mixins.py
drf_spreadsheets/renderers.py
drf_spreadsheets-1.1.3.dist-info/LICENSE
drf_spreadsheets-1.1.3.dist-info/METADATA
drf_spreadsheets-1.1.3.dist-info/WHEEL
drf_spreadsheets-1.1.3.dist-info/top_level.txt
drf_spreadsheets-1.1.3.dist-info/RECORD
