Metadata-Version: 2.1
Name: drf-spreadsheets
Version: 1.1.3
Summary: A Django REST Framework package allowing views to be rendered as CSV or XLSX
Home-page: https://github.com/workhere/drf-spreadsheets
Author: Joe Paavola
Author-email: joe@workhere.com
License: UNKNOWN
Platform: UNKNOWN
Classifier: Programming Language :: Python :: 3 :: Only
Classifier: License :: OSI Approved :: MIT License
Classifier: Operating System :: OS Independent
Classifier: Framework :: Django
Classifier: Framework :: Django :: 3.1
Classifier: Development Status :: 3 - Alpha
Requires-Python: >=3.6
Requires-Dist: djangorestframework (>=3.6)
Requires-Dist: openpyxl (>=2.4)
